pynso/__init__.py
pynso/client.py
pynso/connection.py
pynso/datastores.py
pynso/types.py
pynso_restconf-2.1.2.dist-info/LICENSE
pynso_restconf-2.1.2.dist-info/WHEEL
pynso_restconf-2.1.2.dist-info/METADATA
pynso_restconf-2.1.2.dist-info/RECORD
